{
  "name": "LANDER Wheels",
  "bio": "<p>Established in 2007, Lander Wheels has been a leading innovator in the design and manufacturing of wheels for off-road, street, and track use. Originally founded as a specialist in wheels for the off-road racing sector, Lander Wheels' commitment to performance continues to drive its entire product lineup. Customers can rely on Lander Wheels for cutting-edge technology and superior quality across a wide range of aftermarket wheel styles and fitments for passenger cars, light trucks, SUVs, and UTVs.</p>",
  "thumb": "about-left-thumb.jpg",
  "socialMedia": [
    {
      "id": 1,
      "media": "instagram",
      "icon": "FaInstagram",
      "link": "https://www.instagram.com/landerwheels/"
    }
  ]
}